<?xml version="1.0" encoding="UTF-8"?>
<thing:thing-descriptions bindingId="tmaso" xmlns:xsi="http://www.w3.org/2001/XMLSchema-instance"
	xmlns:thing="http://eclipse.org/smarthome/schemas/thing-description/v1.0.0"
	xsi:schemaLocation="http://eclipse.org/smarthome/schemas/thing-description/v1.0.0 http://eclipse.org/smarthome/schemas/thing-description-1.0.0.xsd">

	<thing-type id="rfid">
		<label>RFID Reader</label>
		<description>RFID Reader which help to authenticate user access</description>
		<channels>
			<channel id="default" typeId="rfidDefaultChannel" />
		</channels>
		<config-description>
		<!-- 
			<parameter name="pingtime" type="integer" required="true">
				<context>pingtime</context>
				<label>Ping Time</label>
				<description>Time to send MQTT ping packet in minutes.</description>
				<default>5</default>
			</parameter>
		 -->
		</config-description>
	</thing-type>
	<channel-type id="rfidDefaultChannel" advanced="true">
        <item-type>Switch</item-type>
        <label>RFID Authenticator</label>
        <description>Authenticate user access using RFID card</description>
        <category>Sensor</category>
        <tags>
            <tag>Sensor</tag>
        </tags>
    </channel-type>
</thing:thing-descriptions>
